MANIFEST.in
README.md
setup.cfg
setup.py
ipyfileupload/__init__.py
ipyfileupload/_version.py
ipyfileupload/widgets.py
ipyfileupload.egg-info/PKG-INFO
ipyfileupload.egg-info/SOURCES.txt
ipyfileupload.egg-info/dependency_links.txt
ipyfileupload.egg-info/not-zip-safe
ipyfileupload.egg-info/requires.txt
ipyfileupload.egg-info/top_level.txt
ipyfileupload/static/extension.js
ipyfileupload/static/index.js
ipyfileupload/static/index.js.map